easynetwork_trio/__init__.py
easynetwork_trio/py.typed
easynetwork_trio-0.1.0.dev0.dist-info/METADATA
easynetwork_trio-0.1.0.dev0.dist-info/WHEEL
easynetwork_trio-0.1.0.dev0.dist-info/licenses/LICENSE
easynetwork_trio-0.1.0.dev0.dist-info/RECORD
